notte_core/__init__.py
notte_core/agent_types.py
notte_core/ast.py
notte_core/config.toml
notte_core/profiling.py
notte_core/py.typed
notte_core/space.py
notte_core/storage.py
notte_core/trajectory.py
notte_core/actions/__init__.py
notte_core/actions/actions.py
notte_core/actions/typedicts.py
notte_core/browser/__init__.py
notte_core/browser/dom_tree.py
notte_core/browser/highlighter.py
notte_core/browser/node_type.py
notte_core/browser/observation.py
notte_core/browser/perception.py
notte_core/browser/snapshot.py
notte_core/common/__init__.py
notte_core/common/cache.py
notte_core/common/config.py
notte_core/common/logging.py
notte_core/common/notifier.py
notte_core/common/resource.py
notte_core/common/telemetry.py
notte_core/common/types.py
notte_core/credentials/__init__.py
notte_core/credentials/base.py
notte_core/credentials/types.py
notte_core/data/__init__.py
notte_core/data/space.py
notte_core/errors/__init__.py
notte_core/errors/actions.py
notte_core/errors/base.py
notte_core/errors/llm.py
notte_core/errors/processing.py
notte_core/errors/provider.py
notte_core/errors/validation.py
notte_core/utils/OpenSansEmoji.otf
notte_core/utils/__init__.py
notte_core/utils/code.py
notte_core/utils/encryption.py
notte_core/utils/files.py
notte_core/utils/image.py
notte_core/utils/platform.py
notte_core/utils/pydantic_schema.py
notte_core/utils/raw_file.py
notte_core/utils/singleton.py
notte_core/utils/url.py
notte_core/utils/webp_replay.py
notte_core-1.8.3.dist-info/METADATA
notte_core-1.8.3.dist-info/WHEEL
notte_core-1.8.3.dist-info/RECORD
