Metadata-Version: 2.4
Name: notte-core
Version: 1.8.3
Summary: The web browser for LLMs agents
Author-email: Notte Team  <hello@notte.cc>
Requires-Python: >=3.11
Requires-Dist: aiohttp~=3.11.13
Requires-Dist: cryptography>=43.0.3
Requires-Dist: loguru>=0.7.3
Requires-Dist: nest-asyncio>=1.6.0
Requires-Dist: opentelemetry-sdk>=1.34.1
Requires-Dist: packaging>=25.0
Requires-Dist: pillow>=11.1.0
Requires-Dist: posthog<=7.0.1,>=3.0.1
Requires-Dist: pydantic-settings>=2.8.1
Requires-Dist: pydantic>=2.10.6
Requires-Dist: pyotp>=2.9.0
Requires-Dist: python-dotenv>=1.0.1
Requires-Dist: requests>=2.32.3
Requires-Dist: restrictedpython>=8.0
Requires-Dist: scarf-sdk>=0.1.2
Requires-Dist: tldextract>=5.3.0
Requires-Dist: toml>=0.10.2
Provides-Extra: observability
Requires-Dist: opentelemetry-exporter-otlp>=1.27.0; extra == 'observability'
Requires-Dist: pyroscope-io>=0.8.0; extra == 'observability'
Requires-Dist: pyroscope-otel>=0.1.0; extra == 'observability'
Provides-Extra: pyroscope
Requires-Dist: pyroscope-io>=0.8.0; extra == 'pyroscope'
Requires-Dist: pyroscope-otel>=0.1.0; extra == 'pyroscope'
Provides-Extra: tempo
Requires-Dist: opentelemetry-exporter-otlp>=1.27.0; extra == 'tempo'
